wrap_data_source/__init__.py
wrap_data_source/costume_loader.py
wrap_data_source/data_source.py
wrap_data_source/file_data_source.py
wrap_data_source/settings.py
wrap_data_source-0.1.0.dist-info/METADATA
wrap_data_source-0.1.0.dist-info/WHEEL
wrap_data_source-0.1.0.dist-info/top_level.txt
wrap_data_source-0.1.0.dist-info/RECORD
